Metadata-Version: 2.1
Name: scrapertools
Version: 1.7.5
Summary: scraping for humans
Home-page: https://github.com/ultrafunkamsterdam/scrapertools
Author: UltrafunkAmsterdam
Author-email: info@ultrafunk.nl
License: GPL3.0 License
Platform: UNKNOWN
Classifier: License :: OSI Approved :: GNU General Public License v3 (GPLv3)
Classifier: Programming Language :: Python :: 3
Classifier: Programming Language :: Python :: 3.7
Provides-Extra: video
